fedai/__init__.py
fedai/client.py
fedai/constants.py
fedai-0.7.0.dist-info/METADATA
fedai-0.7.0.dist-info/WHEEL
fedai-0.7.0.dist-info/top_level.txt
fedai-0.7.0.dist-info/RECORD
