Metadata-Version: 2.1
Name: fedai
Version: 0.7.0
Summary: Xeniro Federated Learning Tools
Home-page: UNKNOWN
Author: UNKNOWN
Author-email: UNKNOWN
License: UNKNOWN
Platform: UNKNOWN
Requires-Dist: joblib
Requires-Dist: numpy
Requires-Dist: pandas
Requires-Dist: tqdm
